Metadata-Version: 2.1
Name: rand-calc-guess
Version: 0.0.1
Summary: A lib of random generator, games and calculator
Home-page: UNKNOWN
Author: Anoosha Tanseer
Author-email: atanseer2016@gmail.com
License: UNKNOWN
Keywords: python,random,timer,area,game,guess,madlib,countdown,addition,mod,password,shape
Platform: UNKNOWN
Classifier: Development Status :: 1 - Planning
Classifier: Intended Audience :: Developers
Classifier: Programming Language :: Python :: 3
Classifier: Operating System :: Unix
Classifier: Operating System :: MacOS :: MacOS X
Classifier: Operating System :: Microsoft :: Windows
License-File: LICENSE
